{"bb_code": "1500858002600283", "bb_year": "2562", "amount": 2470000, "min_code": "15000", "agc_code": "15008", "name": "ก่อสร้างอาคารศูนย์พัฒนาเด็กเล็ก ขนาด 51 - 80 คน ตอกเสาเข็ม ศูนย์พัฒนาเด็กเล็กบ้านเนินสายฝน องค์การบริหารส่วนตำบลพระเพลิง อำเภอเขาฉกรรจ์จังหวัดสระแก้ว", "min": "กระทรวงมหาดไทย", "agc": "กรมส่งเสริมการปกครองท้องถิ่น", "plan_name": "แผนงานบูรณาการส่งเสริมการกระจายอำนาจให้แก่องค์กรปกครองส่วนท้องถิ่น", "stg_name": "ยุทธศาสตร์ด้านการปรับสมดุลและพัฒนาระบบบริหารจัดการภาครัฐ", "objc_level1_name": "งบอุดหนุน", "compare": [{"bb_amount": 2470000, "bb_province": "สระแก้ว", "gf_amount": 0, "gf_province": "สระแก้ว"}], "gf_amount_sum": 0}
{"bb_code": "1500858002600284", "bb_year": "2562", "amount": 2470000, "min_code": "15000", "agc_code": "15008", "name": "ก่อสร้างอาคารศูนย์พัฒนาเด็กเล็ก ขนาด 51 - 80 คน ตอกเสาเข็ม ศูนย์พัฒนาเด็กเล็กบ้านซับมะนาว องค์การบริหารส่วนตำบลหนองหว้า อำเภอเขาฉกรรจ์ จังหวัดสระแก้ว", "min": "กระทรวงมหาดไทย", "agc": "กรมส่งเสริมการปกครองท้องถิ่น", "plan_name": "แผนงานบูรณาการส่งเสริมการกระจายอำนาจให้แก่องค์กรปกครองส่วนท้องถิ่น", "stg_name": "ยุทธศาสตร์ด้านการปรับสมดุลและพัฒนาระบบบริหารจัดการภาครัฐ", "objc_level1_name": "งบอุดหนุน", "compare": [{"bb_amount": 2470000, "bb_province": "สระแก้ว", "gf_amount": 0, "gf_province": "สระแก้ว"}], "gf_amount_sum": 0}
{"bb_code": "1500858002600286", "bb_year": "2562", "amount": 2470000, "min_code": "15000", "agc_code": "15008", "name": "ก่อสร้างอาคารศูนย์พัฒนาเด็กเล็ก ขนาด 51 - 80 คน ตอกเสาเข็ม ศูนย์พัฒนาเด็กเล็กบ้านทุ่งพระ องค์การบริหารส่วนตำบลท่าเกษม อำเภอเมืองสระแก้วจังหวัดสระแก้ว", "min": "กระทรวงมหาดไทย", "agc": "กรมส่งเสริมการปกครองท้องถิ่น", "plan_name": "แผนงานบูรณาการส่งเสริมการกระจายอำนาจให้แก่องค์กรปกครองส่วนท้องถิ่น", "stg_name": "ยุทธศาสตร์ด้านการปรับสมดุลและพัฒนาระบบบริหารจัดการภาครัฐ", "objc_level1_name": "งบอุดหนุน", "compare": [{"bb_amount": 2470000, "bb_province": "สระแก้ว", "gf_amount": 0, "gf_province": "สระแก้ว"}], "gf_amount_sum": 0}
{"bb_code": "1500858002600287", "bb_year": "2562", "amount": 2470000, "min_code": "15000", "agc_code": "15008", "name": "ก่อสร้างอาคารศูนย์พัฒนาเด็กเล็ก ขนาด 51 - 80 คน ตอกเสาเข็ม ศูนย์พัฒนาเด็กเล็ก รร.บ้านหนองขี้เห็น องค์การบริหารส่วนตำบลโคกปี่ฆ้อง อำเภอเมืองสระแก้ว จังหวัดสระแก้ว", "min": "กระทรวงมหาดไทย", "agc": "กรมส่งเสริมการปกครองท้องถิ่น", "plan_name": "แผนงานบูรณาการส่งเสริมการกระจายอำนาจให้แก่องค์กรปกครองส่วนท้องถิ่น", "stg_name": "ยุทธศาสตร์ด้านการปรับสมดุลและพัฒนาระบบบริหารจัดการภาครัฐ", "objc_level1_name": "งบอุดหนุน", "compare": [{"bb_amount": 2470000, "bb_province": "สระแก้ว", "gf_amount": 0, "gf_province": "สระแก้ว"}], "gf_amount_sum": 0}
{"bb_code": "1500858002600288", "bb_year": "2562", "amount": 2470000, "min_code": "15000", "agc_code": "15008", "name": "ก่อสร้างอาคารศูนย์พัฒนาเด็กเล็ก ขนาด 51 - 80 คน ตอกเสาเข็ม ศูนย์พัฒนาเด็กเล็กบ้านซับเจริญ องค์การบริหารส่วนตำบลทุ่งมหาเจริญ อำเภอวังน้ำเย็น จังหวัดสระแก้ว", "min": "กระทรวงมหาดไทย", "agc": "กรมส่งเสริมการปกครองท้องถิ่น", "plan_name": "แผนงานบูรณาการส่งเสริมการกระจายอำนาจให้แก่องค์กรปกครองส่วนท้องถิ่น", "stg_name": "ยุทธศาสตร์ด้านการปรับสมดุลและพัฒนาระบบบริหารจัดการภาครัฐ", "objc_level1_name": "งบอุดหนุน", "compare": [{"bb_amount": 2470000, "bb_province": "สระแก้ว", "gf_amount": 0, "gf_province": "สระแก้ว"}], "gf_amount_sum": 0}
{"bb_code": "1500858002600289", "bb_year": "2562", "amount": 2470000, "min_code": "15000", "agc_code": "15008", "name": "ก่อสร้างอาคารศูนย์พัฒนาเด็กเล็ก ขนาด 51 - 80 คน ตอกเสาเข็ม ศูนย์พัฒนาเด็กเล็กบ้านวังสำลี องค์การบริหารส่วนตำบลวังใหม่ อำเภอวังสมบูรณ์ จังหวัดสระแก้ว", "min": "กระทรวงมหาดไทย", "agc": "กรมส่งเสริมการปกครองท้องถิ่น", "plan_name": "แผนงานบูรณาการส่งเสริมการกระจายอำนาจให้แก่องค์กรปกครองส่วนท้องถิ่น", "stg_name": "ยุทธศาสตร์ด้านการปรับสมดุลและพัฒนาระบบบริหารจัดการภาครัฐ", "objc_level1_name": "งบอุดหนุน", "compare": [{"bb_amount": 2470000, "bb_province": "สระแก้ว", "gf_amount": 0, "gf_province": "สระแก้ว"}], "gf_amount_sum": 0}
{"bb_code": "1500858002600290", "bb_year": "2562", "amount": 2470000, "min_code": "15000", "agc_code": "15008", "name": "ก่อสร้างอาคารศูนย์พัฒนาเด็กเล็ก ขนาด 51 - 80 คน ตอกเสาเข็ม ศูนย์พัฒนาเด็กเล็กบ้านช่องกุ่ม องค์การบริหารส่วนตำบลช่องกุ่ม อำเภอวัฒนานคร จังหวัดสระแก้ว", "min": "กระทรวงมหาดไทย", "agc": "กรมส่งเสริมการปกครองท้องถิ่น", "plan_name": "แผนงานบูรณาการส่งเสริมการกระจายอำนาจให้แก่องค์กรปกครองส่วนท้องถิ่น", "stg_name": "ยุทธศาสตร์ด้านการปรับสมดุลและพัฒนาระบบบริหารจัดการภาครัฐ", "objc_level1_name": "งบอุดหนุน", "compare": [{"bb_amount": 2470000, "bb_province": "สระแก้ว", "gf_amount": 0, "gf_province": "สระแก้ว"}], "gf_amount_sum": 0}
{"bb_code": "1500858002600291", "bb_year": "2562", "amount": 2470000, "min_code": "15000", "agc_code": "15008", "name": "ก่อสร้างอาคารศูนย์พัฒนาเด็กเล็ก ขนาด 51 - 80 คน ตอกเสาเข็ม ศูนย์พัฒนาเด็กเล็ก รร.วัดพระพุทธบาทน้อย มิตรภาพที่69 องค์การบริหารส่วนตำบลสองคอน อำเภอแก่งคอย จังหวัดสระบุรี", "min": "กระทรวงมหาดไทย", "agc": "กรมส่งเสริมการปกครองท้องถิ่น", "plan_name": "แผนงานบูรณาการส่งเสริมการกระจายอำนาจให้แก่องค์กรปกครองส่วนท้องถิ่น", "stg_name": "ยุทธศาสตร์ด้านการปรับสมดุลและพัฒนาระบบบริหารจัดการภาครัฐ", "objc_level1_name": "งบอุดหนุน", "compare": [{"bb_amount": 2470000, "bb_province": "สระบุรี", "gf_amount": 0, "gf_province": "สระบุรี"}], "gf_amount_sum": 0}
{"bb_code": "1500858002600292", "bb_year": "2562", "amount": 2470000, "min_code": "15000", "agc_code": "15008", "name": "ก่อสร้างอาคารศูนย์พัฒนาเด็กเล็ก ขนาด 51 - 80 คน ตอกเสาเข็ม ศูนย์พัฒนาเด็กเล็กเทศบาลตำบลสร่างโศก เทศบาลตำบลสร่างโศก อำเภอบ้านหมอจังหวัดสระบุรี", "min": "กระทรวงมหาดไทย", "agc": "กรมส่งเสริมการปกครองท้องถิ่น", "plan_name": "แผนงานบูรณาการส่งเสริมการกระจายอำนาจให้แก่องค์กรปกครองส่วนท้องถิ่น", "stg_name": "ยุทธศาสตร์ด้านการปรับสมดุลและพัฒนาระบบบริหารจัดการภาครัฐ", "objc_level1_name": "งบอุดหนุน", "compare": [{"bb_amount": 2470000, "bb_province": "สระบุรี", "gf_amount": 0, "gf_province": "สระบุรี"}], "gf_amount_sum": 0}
{"bb_code": "1500858002600294", "bb_year": "2562", "amount": 2470000, "min_code": "15000", "agc_code": "15008", "name": "ก่อสร้างอาคารศูนย์พัฒนาเด็กเล็ก ขนาด 51 - 80 คน ตอกเสาเข็ม ศูนย์พัฒนาเด็กเล็กองค์การบริหารส่วนตำบลวิหารแดง องค์การบริหารส่วนตำบลวิหารแดง อำเภอวิหารแดงจังหวัดสระบุรี", "min": "กระทรวงมหาดไทย", "agc": "กรมส่งเสริมการปกครองท้องถิ่น", "plan_name": "แผนงานบูรณาการส่งเสริมการกระจายอำนาจให้แก่องค์กรปกครองส่วนท้องถิ่น", "stg_name": "ยุทธศาสตร์ด้านการปรับสมดุลและพัฒนาระบบบริหารจัดการภาครัฐ", "objc_level1_name": "งบอุดหนุน", "compare": [{"bb_amount": 2470000, "bb_province": "สระบุรี", "gf_amount": 0, "gf_province": "สระบุรี"}], "gf_amount_sum": 0}
{"bb_code": "1500858002600295", "bb_year": "2562", "amount": 2470000, "min_code": "15000", "agc_code": "15008", "name": "ก่อสร้างอาคารศูนย์พัฒนาเด็กเล็ก ขนาด 51 - 80 คน ตอกเสาเข็ม ศูนย์พัฒนาเด็กเล็กเทศบาลตำบลหน้าพระลานเทศบาลตำบลหน้าพระลานอำเภอเฉลิมพระเกียรติ จังหวัดสระบุรี", "min": "กระทรวงมหาดไทย", "agc": "กรมส่งเสริมการปกครองท้องถิ่น", "plan_name": "แผนงานบูรณาการส่งเสริมการกระจายอำนาจให้แก่องค์กรปกครองส่วนท้องถิ่น", "stg_name": "ยุทธศาสตร์ด้านการปรับสมดุลและพัฒนาระบบบริหารจัดการภาครัฐ", "objc_level1_name": "งบอุดหนุน", "compare": [{"bb_amount": 2470000, "bb_province": "สระบุรี", "gf_amount": 0, "gf_province": "สระบุรี"}], "gf_amount_sum": 0}
{"bb_code": "1500858002600296", "bb_year": "2562", "amount": 2470000, "min_code": "15000", "agc_code": "15008", "name": "ก่อสร้างอาคารศูนย์พัฒนาเด็กเล็ก ขนาด 51-80 คน ตอกเสาเข็ม ศูนย์พัฒนาเด็กเล็กวัดเชิงผา เทศบาลตำบลกลางดงอำเภอทุ่งเสลี่ยม จังหวัดสุโขทัย", "min": "กระทรวงมหาดไทย", "agc": "กรมส่งเสริมการปกครองท้องถิ่น", "plan_name": "แผนงานบูรณาการส่งเสริมการกระจายอำนาจให้แก่องค์กรปกครองส่วนท้องถิ่น", "stg_name": "ยุทธศาสตร์ด้านการปรับสมดุลและพัฒนาระบบบริหารจัดการภาครัฐ", "objc_level1_name": "งบอุดหนุน", "compare": [{"bb_amount": 2470000, "bb_province": "สุโขทัย", "gf_amount": 0, "gf_province": "สุโขทัย"}], "gf_amount_sum": 0}
{"bb_code": "1500858002600298", "bb_year": "2562", "amount": 2470000, "min_code": "15000", "agc_code": "15008", "name": "ก่อสร้างอาคารศูนย์พัฒนาเด็กเล็ก ขนาด 51-80 คน ตอกเสาเข็ม ศูนย์พัฒนาเด็กเล็กองค์การบริหารส่วนตำบลบ้านสวน(วัดจันทร์) องค์การบริหารส่วนตำบลบ้านสวน อำเภอเมืองสุโขทัย จังหวัดสุโขทัย", "min": "กระทรวงมหาดไทย", "agc": "กรมส่งเสริมการปกครองท้องถิ่น", "plan_name": "แผนงานบูรณาการส่งเสริมการกระจายอำนาจให้แก่องค์กรปกครองส่วนท้องถิ่น", "stg_name": "ยุทธศาสตร์ด้านการปรับสมดุลและพัฒนาระบบบริหารจัดการภาครัฐ", "objc_level1_name": "งบอุดหนุน", "compare": [{"bb_amount": 2470000, "bb_province": "สุโขทัย", "gf_amount": 0, "gf_province": "สุโขทัย"}], "gf_amount_sum": 0}
{"bb_code": "1500858002600299", "bb_year": "2562", "amount": 2470000, "min_code": "15000", "agc_code": "15008", "name": "ก่อสร้างอาคารศูนย์พัฒนาเด็กเล็ก ขนาด 51-80 คน ตอกเสาเข็ม ศูนย์พัฒนาเด็กเล็ก รร.บ้านโซกเปือย องค์การบริหารส่วนตำบลนาขุนไกร อำเภอศรีสำโรง จังหวัดสุโขทัย", "min": "กระทรวงมหาดไทย", "agc": "กรมส่งเสริมการปกครองท้องถิ่น", "plan_name": "แผนงานบูรณาการส่งเสริมการกระจายอำนาจให้แก่องค์กรปกครองส่วนท้องถิ่น", "stg_name": "ยุทธศาสตร์ด้านการปรับสมดุลและพัฒนาระบบบริหารจัดการภาครัฐ", "objc_level1_name": "งบอุดหนุน", "compare": [{"bb_amount": 2470000, "bb_province": "สุโขทัย", "gf_amount": 0, "gf_province": "สุโขทัย"}], "gf_amount_sum": 0}
{"bb_code": "1500858002600300", "bb_year": "2562", "amount": 2470000, "min_code": "15000", "agc_code": "15008", "name": "ก่อสร้างอาคารศูนย์พัฒนาเด็กเล็ก ขนาด 51-80 คนตอกเสาเข็มศูนย์พัฒนาเด็กเล็กบ้านกรุองค์การบริหารส่วนตำบลสามเรือน อำเภอศรีสำโรง จังหวัดสุโขทัย", "min": "กระทรวงมหาดไทย", "agc": "กรมส่งเสริมการปกครองท้องถิ่น", "plan_name": "แผนงานบูรณาการส่งเสริมการกระจายอำนาจให้แก่องค์กรปกครองส่วนท้องถิ่น", "stg_name": "ยุทธศาสตร์ด้านการปรับสมดุลและพัฒนาระบบบริหารจัดการภาครัฐ", "objc_level1_name": "งบอุดหนุน", "compare": [{"bb_amount": 2470000, "bb_province": "สุโขทัย", "gf_amount": 0, "gf_province": "สุโขทัย"}], "gf_amount_sum": 0}
{"bb_code": "1500858002600302", "bb_year": "2562", "amount": 2470000, "min_code": "15000", "agc_code": "15008", "name": "ก่อสร้างอาคารศูนย์พัฒนาเด็กเล็ก ขนาด 51-80 คน ตอกเสาเข็ม ศูนย์พัฒนาเด็กเล็กบ้านกาบกระบือ องค์การบริหารส่วนตำบลโคกสะอาด อำเภอปราสาทจังหวัดสุรินทร์", "min": "กระทรวงมหาดไทย", "agc": "กรมส่งเสริมการปกครองท้องถิ่น", "plan_name": "แผนงานบูรณาการส่งเสริมการกระจายอำนาจให้แก่องค์กรปกครองส่วนท้องถิ่น", "stg_name": "ยุทธศาสตร์ด้านการปรับสมดุลและพัฒนาระบบบริหารจัดการภาครัฐ", "objc_level1_name": "งบอุดหนุน", "compare": [{"bb_amount": 2470000, "bb_province": "สุรินทร์", "gf_amount": 0, "gf_province": "สุรินทร์"}], "gf_amount_sum": 0}
{"bb_code": "1500858002600303", "bb_year": "2562", "amount": 2470000, "min_code": "15000", "agc_code": "15008", "name": "ก่อสร้างอาคารศูนย์พัฒนาเด็กเล็ก ขนาด 51-80 คน ตอกเสาเข็ม ศูนย์พัฒนาเด็กเล็กองค์การบริหารส่วนตำบลเมืองทีองค์การบริหารส่วนตำบลเมืองทีอำเภอเมืองสุรินทร์ จังหวัดสุรินทร์", "min": "กระทรวงมหาดไทย", "agc": "กรมส่งเสริมการปกครองท้องถิ่น", "plan_name": "แผนงานบูรณาการส่งเสริมการกระจายอำนาจให้แก่องค์กรปกครองส่วนท้องถิ่น", "stg_name": "ยุทธศาสตร์ด้านการปรับสมดุลและพัฒนาระบบบริหารจัดการภาครัฐ", "objc_level1_name": "งบอุดหนุน", "compare": [{"bb_amount": 2470000, "bb_province": "สุรินทร์", "gf_amount": 0, "gf_province": "สุรินทร์"}], "gf_amount_sum": 0}
{"bb_code": "1500858002600304", "bb_year": "2562", "amount": 2470000, "min_code": "15000", "agc_code": "15008", "name": "ก่อสร้างอาคารศูนย์พัฒนาเด็กเล็ก ขนาด 51-80 คน ตอกเสาเข็ม ศูนย์พัฒนาเด็กเล็กบ้านสว่าง-โนนแดง องค์การบริหารส่วนตำบลยาง อำเภอศีขรภูมิจังหวัดสุรินทร์", "min": "กระทรวงมหาดไทย", "agc": "กรมส่งเสริมการปกครองท้องถิ่น", "plan_name": "แผนงานบูรณาการส่งเสริมการกระจายอำนาจให้แก่องค์กรปกครองส่วนท้องถิ่น", "stg_name": "ยุทธศาสตร์ด้านการปรับสมดุลและพัฒนาระบบบริหารจัดการภาครัฐ", "objc_level1_name": "งบอุดหนุน", "compare": [{"bb_amount": 2470000, "bb_province": "สุรินทร์", "gf_amount": 0, "gf_province": "สุรินทร์"}], "gf_amount_sum": 0}
{"bb_code": "1500858002600306", "bb_year": "2562", "amount": 2470000, "min_code": "15000", "agc_code": "15008", "name": "ก่อสร้างอาคารศูนย์พัฒนาเด็กเล็ก ขนาด 51-80 คน ตอกเสาเข็ม ศูนย์พัฒนาเด็กเล็กบ้านตาแตรว องค์การบริหารส่วนตำบลเทพรักษา อำเภอสังขะ จังหวัดสุรินทร์", "min": "กระทรวงมหาดไทย", "agc": "กรมส่งเสริมการปกครองท้องถิ่น", "plan_name": "แผนงานบูรณาการส่งเสริมการกระจายอำนาจให้แก่องค์กรปกครองส่วนท้องถิ่น", "stg_name": "ยุทธศาสตร์ด้านการปรับสมดุลและพัฒนาระบบบริหารจัดการภาครัฐ", "objc_level1_name": "งบอุดหนุน", "compare": [{"bb_amount": 2470000, "bb_province": "สุรินทร์", "gf_amount": 0, "gf_province": "สุรินทร์"}], "gf_amount_sum": 0}
{"bb_code": "1500858002600307", "bb_year": "2562", "amount": 2470000, "min_code": "15000", "agc_code": "15008", "name": "ก่อสร้างอาคารศูนย์พัฒนาเด็กเล็ก ขนาด 51-80ตอกเสาเข็มศูนย์พัฒนาเด็กเล็กบ้านหองแดงเทศบาลตำบลโพธิ์ชัย อำเภอเมืองหนองคาย จังหวัดหนองคาย", "min": "กระทรวงมหาดไทย", "agc": "กรมส่งเสริมการปกครองท้องถิ่น", "plan_name": "แผนงานบูรณาการส่งเสริมการกระจายอำนาจให้แก่องค์กรปกครองส่วนท้องถิ่น", "stg_name": "ยุทธศาสตร์ด้านการปรับสมดุลและพัฒนาระบบบริหารจัดการภาครัฐ", "objc_level1_name": "งบอุดหนุน", "compare": [{"bb_amount": 2470000, "bb_province": "หนองคาย", "gf_amount": 0, "gf_province": "หนองคาย"}], "gf_amount_sum": 0}
