{"bb_code": "1500856063120001", "bb_year": "2561", "amount": 30572000, "min_code": "15000", "agc_code": "15008", "name": "ค่าใช้จ่ายในการเพิ่มประสิทธิภาพเครื่องคอมพิวเตอร์แม่ข่ายของระบบบัญชีคอมพิวเตอร์ขององค์กรปกครองส่วนท้องถิ่น (e-LAAS)กรมส่งเสริมการปกครองท้องถิ่น แขวงดุสิต เขตดุสิตกรุงเทพมหานคร", "min": "กระทรวงมหาดไทย", "agc": "กรมส่งเสริมการปกครองท้องถิ่น", "plan_name": "แผนงานยุทธศาสตร์พัฒนาประสิทธิภาพการบริหารราชการแผ่นดิน", "stg_name": "ยุทธศาสตร์ด้านการปรับสมดุลและพัฒนาระบบบริหารจัดการภาครัฐ", "objc_level1_name": "งบลงทุน", "compare": [{"bb_amount": 30572000, "bb_province": "กรุงเทพมหานคร", "gf_amount": 24200000, "gf_province": "ส่วนกลาง"}], "gf_amount_sum": 24200000}
{"bb_code": "1500953045500001", "bb_year": "2561", "amount": 30340300, "min_code": "15000", "agc_code": "15009", "name": "งานแก้ไขปัญหายาเสพติดในพื้นที่กรุงเทพมหานคร", "min": "กระทรวงมหาดไทย", "agc": "กรุงเทพมหานคร", "plan_name": "แผนงานบูรณาการส่งเสริมการกระจายอำนาจให้แก่องค์กรปกครองส่วนท้องถิ่น", "stg_name": "ยุทธศาสตร์ด้านการปรับสมดุลและพัฒนาระบบบริหารจัดการภาครัฐ", "objc_level1_name": "งบอุดหนุน", "compare": [{"bb_amount": 30340300, "bb_province": "กรุงเทพมหานคร", "gf_amount": 30340300, "gf_province": "ส่วนกลาง"}], "gf_amount_sum": 30340300}
{"bb_code": "1500746037700045", "bb_year": "2561", "amount": 30000000, "min_code": "15000", "agc_code": "15007", "name": "โครงการพัฒนาระบบข้อมูลด้านคมนาคมขนส่งเพื่อการพัฒนาตามผังประเทศ", "min": "กระทรวงมหาดไทย", "agc": "กรมโยธาธิการและผังเมือง", "plan_name": "แผนงานยุทธศาสตร์อนุรักษ์ ฟื้นฟู และป้องกันทรัพยากรธรรมชาติ", "stg_name": "ยุทธศาสตร์ด้านการจัดการน้ำและสร้างการเติบโตบนคุณภาพชีวิตที่เป็นมิตรกับสิ่งแวดล้อมอย่างยั่งยืน", "objc_level1_name": "รายจ่ายอื่น", "compare": [{"bb_amount": 30000000, "bb_province": "กรุงเทพมหานคร", "gf_amount": 0, "gf_province": "ส่วนกลาง"}], "gf_amount_sum": 0}
{"bb_code": "1500746037700093", "bb_year": "2561", "amount": 30000000, "min_code": "15000", "agc_code": "15007", "name": "โครงการพัฒนาระบบข้อมูลด้านโครงสร้างพื้นฐานเพื่อการพัฒนาตามผังประเทศ", "min": "กระทรวงมหาดไทย", "agc": "กรมโยธาธิการและผังเมือง", "plan_name": "แผนงานยุทธศาสตร์อนุรักษ์ ฟื้นฟู และป้องกันทรัพยากรธรรมชาติ", "stg_name": "ยุทธศาสตร์ด้านการจัดการน้ำและสร้างการเติบโตบนคุณภาพชีวิตที่เป็นมิตรกับสิ่งแวดล้อมอย่างยั่งยืน", "objc_level1_name": "รายจ่ายอื่น", "compare": [{"bb_amount": 30000000, "bb_province": "กรุงเทพมหานคร", "gf_amount": 0, "gf_province": "ส่วนกลาง"}], "gf_amount_sum": 0}
{"bb_code": "1500747026420141", "bb_year": "2561", "amount": 30000000, "min_code": "15000", "agc_code": "15007", "name": "ค่าสำรวจออกแบบและควบคุมงาน", "min": "กระทรวงมหาดไทย", "agc": "กรมโยธาธิการและผังเมือง", "plan_name": "แผนงานยุทธศาสตร์จัดการผลกระทบจากการเปลี่ยนแปลงสภาวะภูมิอากาศ และภัยพิบัติ", "stg_name": "ยุทธศาสตร์ด้านการจัดการน้ำและสร้างการเติบโตบนคุณภาพชีวิตที่เป็นมิตรกับสิ่งแวดล้อมอย่างยั่งยืน", "objc_level1_name": "งบลงทุน", "compare": [{"bb_amount": 30000000, "bb_province": "กรุงเทพมหานคร", "gf_amount": 11689008.66, "gf_province": "ส่วนกลาง"}, {"gf_amount": 525000, "gf_province": "น่าน", "bb_amount": null, "bb_province": "น่าน"}, {"gf_amount": 521280, "gf_province": "แม่ฮ่องสอน", "bb_amount": null, "bb_province": "แม่ฮ่องสอน"}, {"gf_amount": 363199.42, "gf_province": "พะเยา", "bb_amount": null, "bb_province": "พะเยา"}, {"gf_amount": 234000, "gf_province": "พังงา", "bb_amount": null, "bb_province": "พังงา"}, {"gf_amount": 199999.3, "gf_province": "นครสวรรค์", "bb_amount": null, "bb_province": "นครสวรรค์"}, {"gf_amount": 198947, "gf_province": "พิจิตร", "bb_amount": null, "bb_province": "พิจิตร"}], "gf_amount_sum": 13731434.38}
{"bb_code": "1500256039120003", "bb_year": "2561", "amount": 29780000, "min_code": "15000", "agc_code": "15002", "name": "รถยนต์ตรวจการณ์ ปริมาตรกระบอกสูบไม่ต่ำกว่า 2,000ซีซี หรือกำลังเครื่องยนต์สูงสุดไม่ต่ำกว่า 110 กิโลวัตต์เครื่องยนต์ดีเซล แบบขับเคลื่อน 4 ล้อ", "min": "กระทรวงมหาดไทย", "agc": "สำนักงานปลัดกระทรวงมหาดไทย", "plan_name": "แผนงานยุทธศาสตร์พัฒนาประสิทธิภาพการบริหารราชการแผ่นดิน", "stg_name": "ยุทธศาสตร์ด้านการปรับสมดุลและพัฒนาระบบบริหารจัดการภาครัฐ", "objc_level1_name": "งบลงทุน", "compare": [{"bb_amount": 29780000, "bb_province": "กรุงเทพมหานคร", "gf_amount": 29580000, "gf_province": "ส่วนกลาง"}], "gf_amount_sum": 29580000}
{"bb_code": "1500953047600006", "bb_year": "2561", "amount": 29304000, "min_code": "15000", "agc_code": "15009", "name": "โครงการก่อสร้างระบบระบายน้ำเพื่อแก้ไขปัญหาน้ำท่วมซอยสุขุมวิท 14", "min": "กระทรวงมหาดไทย", "agc": "กรุงเทพมหานคร", "plan_name": "แผนงานบูรณาการส่งเสริมการกระจายอำนาจให้แก่องค์กรปกครองส่วนท้องถิ่น", "stg_name": "ยุทธศาสตร์ด้านการปรับสมดุลและพัฒนาระบบบริหารจัดการภาครัฐ", "objc_level1_name": "งบอุดหนุน", "compare": [{"bb_amount": 29304000, "bb_province": "กรุงเทพมหานคร", "gf_amount": 0, "gf_province": "ส่วนกลาง"}], "gf_amount_sum": 0}
{"bb_code": "1500356031410001", "bb_year": "2561", "amount": 29300000, "min_code": "15000", "agc_code": "15003", "name": "ค่าปรับปรุงอาคารที่ทำการและสิ่งก่อสร้างประกอบ", "min": "กระทรวงมหาดไทย", "agc": "กรมการปกครอง", "plan_name": "แผนงานยุทธศาสตร์พัฒนาประสิทธิภาพการบริหารราชการแผ่นดิน", "stg_name": "ยุทธศาสตร์ด้านการปรับสมดุลและพัฒนาระบบบริหารจัดการภาครัฐ", "objc_level1_name": "งบลงทุน", "compare": [{"bb_amount": 29300000, "bb_province": "กรุงเทพมหานคร", "gf_amount": 0, "gf_province": "ส่วนกลาง"}, {"gf_amount": 1318500, "gf_province": "อุดรธานี", "bb_amount": null, "bb_province": "อุดรธานี"}, {"gf_amount": 1247949, "gf_province": "บุรีรัมย์", "bb_amount": null, "bb_province": "บุรีรัมย์"}, {"gf_amount": 1025500, "gf_province": "เชียงใหม่", "bb_amount": null, "bb_province": "เชียงใหม่"}, {"gf_amount": 1025500, "gf_province": "ขอนแก่น", "bb_amount": null, "bb_province": "ขอนแก่น"}, {"gf_amount": 1025500, "gf_province": "สกลนคร", "bb_amount": null, "bb_province": "สกลนคร"}, {"gf_amount": 1020723, "gf_province": "ศรีสะเกษ", "bb_amount": null, "bb_province": "ศรีสะเกษ"}, {"gf_amount": 879000, "gf_province": "อำนาจเจริญ", "bb_amount": null, "bb_province": "อำนาจเจริญ"}, {"gf_amount": 879000, "gf_province": "นครราชสีมา", "bb_amount": null, "bb_province": "นครราชสีมา"}, {"gf_amount": 879000, "gf_province": "ชัยภูมิ", "bb_amount": null, "bb_province": "ชัยภูมิ"}, {"gf_amount": 879000, "gf_province": "พระนครศรีอยุธยา", "bb_amount": null, "bb_province": "พระนครศรีอยุธยา"}, {"gf_amount": 878400, "gf_province": "ปัตตานี", "bb_amount": null, "bb_province": "ปัตตานี"}, {"gf_amount": 732500, "gf_province": "ตาก", "bb_amount": null, "bb_province": "ตาก"}, {"gf_amount": 732500, "gf_province": "อุบลราชธานี", "bb_amount": null, "bb_province": "อุบลราชธานี"}, {"gf_amount": 732500, "gf_province": "กาฬสินธุ์", "bb_amount": null, "bb_province": "กาฬสินธุ์"}, {"gf_amount": 693200, "gf_province": "สุรินทร์", "bb_amount": null, "bb_province": "สุรินทร์"}, {"gf_amount": 586000, "gf_province": "สระบุรี", "bb_amount": null, "bb_province": "สระบุรี"}, {"gf_amount": 586000, "gf_province": "หนองคาย", "bb_amount": null, "bb_province": "หนองคาย"}, {"gf_amount": 586000, "gf_province": "ฉะเชิงเทรา", "bb_amount": null, "bb_province": "ฉะเชิงเทรา"}, {"gf_amount": 439500, "gf_province": "มหาสารคาม", "bb_amount": null, "bb_province": "มหาสารคาม"}, {"gf_amount": 439500, "gf_province": "ตราด", "bb_amount": null, "bb_province": "ตราด"}, {"gf_amount": 439500, "gf_province": "ลพบุรี", "bb_amount": null, "bb_province": "ลพบุรี"}, {"gf_amount": 439500, "gf_province": "เพชรบูรณ์", "bb_amount": null, "bb_province": "เพชรบูรณ์"}, {"gf_amount": 439500, "gf_province": "พิจิตร", "bb_amount": null, "bb_province": "พิจิตร"}, {"gf_amount": 439500, "gf_province": "สุพรรณบุรี", "bb_amount": null, "bb_province": "สุพรรณบุรี"}, {"gf_amount": 439500, "gf_province": "ชัยนาท", "bb_amount": null, "bb_province": "ชัยนาท"}, {"gf_amount": 439500, "gf_province": "ลำพูน", "bb_amount": null, "bb_province": "ลำพูน"}, {"gf_amount": 439500, "gf_province": "ชลบุรี", "bb_amount": null, "bb_province": "ชลบุรี"}, {"gf_amount": 439500, "gf_province": "นครสวรรค์", "bb_amount": null, "bb_province": "นครสวรรค์"}, {"gf_amount": 438500, "gf_province": "ยโสธร", "bb_amount": null, "bb_province": "ยโสธร"}, {"gf_amount": 438500, "gf_province": "กาญจนบุรี", "bb_amount": null, "bb_province": "กาญจนบุรี"}, {"gf_amount": 436500, "gf_province": "เลย", "bb_amount": null, "bb_province": "เลย"}, {"gf_amount": 435974.4, "gf_province": "พะเยา", "bb_amount": null, "bb_province": "พะเยา"}, {"gf_amount": 433200, "gf_province": "แพร่", "bb_amount": null, "bb_province": "แพร่"}, {"gf_amount": 414500, "gf_province": "ราชบุรี", "bb_amount": null, "bb_province": "ราชบุรี"}, {"gf_amount": 385608, "gf_province": "นราธิวาส", "bb_amount": null, "bb_province": "นราธิวาส"}, {"gf_amount": 293000, "gf_province": "ยะลา", "bb_amount": null, "bb_province": "ยะลา"}, {"gf_amount": 293000, "gf_province": "บึงกาฬ", "bb_amount": null, "bb_province": "บึงกาฬ"}, {"gf_amount": 293000, "gf_province": "สตูล", "bb_amount": null, "bb_province": "สตูล"}, {"gf_amount": 293000, "gf_province": "ลำปาง", "bb_amount": null, "bb_province": "ลำปาง"}, {"gf_amount": 293000, "gf_province": "พิษณุโลก", "bb_amount": null, "bb_province": "พิษณุโลก"}, {"gf_amount": 293000, "gf_province": "ชุมพร", "bb_amount": null, "bb_province": "ชุมพร"}, {"gf_amount": 293000, "gf_province": "สงขลา", "bb_amount": null, "bb_province": "สงขลา"}, {"gf_amount": 293000, "gf_province": "อ่างทอง", "bb_amount": null, "bb_province": "อ่างทอง"}, {"gf_amount": 293000, "gf_province": "สิงห์บุรี", "bb_amount": null, "bb_province": "สิงห์บุรี"}, {"gf_amount": 293000, "gf_province": "ประจวบคีรีขันธ์", "bb_amount": null, "bb_province": "ประจวบคีรีขันธ์"}, {"gf_amount": 292000, "gf_province": "นครศรีธรรมราช", "bb_amount": null, "bb_province": "นครศรีธรรมราช"}, {"gf_amount": 291000, "gf_province": "กำแพงเพชร", "bb_amount": null, "bb_province": "กำแพงเพชร"}, {"gf_amount": 285674, "gf_province": "อุทัยธานี", "bb_amount": null, "bb_province": "อุทัยธานี"}, {"gf_amount": 285500, "gf_province": "จันทบุรี", "bb_amount": null, "bb_province": "จันทบุรี"}, {"gf_amount": 146500, "gf_province": "พัทลุง", "bb_amount": null, "bb_province": "พัทลุง"}, {"gf_amount": 146500, "gf_province": "นครนายก", "bb_amount": null, "bb_province": "นครนายก"}, {"gf_amount": 146500, "gf_province": "สุราษฎร์ธานี", "bb_amount": null, "bb_province": "สุราษฎร์ธานี"}, {"gf_amount": 146500, "gf_province": "สระแก้ว", "bb_amount": null, "bb_province": "สระแก้ว"}, {"gf_amount": 146500, "gf_province": "แม่ฮ่องสอน", "bb_amount": null, "bb_province": "แม่ฮ่องสอน"}, {"gf_amount": 146500, "gf_province": "กระบี่", "bb_amount": null, "bb_province": "กระบี่"}, {"gf_amount": 146500, "gf_province": "ตรัง", "bb_amount": null, "bb_province": "ตรัง"}, {"gf_amount": 146500, "gf_province": "ปทุมธานี", "bb_amount": null, "bb_province": "ปทุมธานี"}, {"gf_amount": 146500, "gf_province": "ปราจีนบุรี", "bb_amount": null, "bb_province": "ปราจีนบุรี"}, {"gf_amount": 146500, "gf_province": "นนทบุรี", "bb_amount": null, "bb_province": "นนทบุรี"}, {"gf_amount": 146500, "gf_province": "สมุทรสงคราม", "bb_amount": null, "bb_province": "สมุทรสงคราม"}, {"gf_amount": 146500, "gf_province": "นครพนม", "bb_amount": null, "bb_province": "นครพนม"}, {"gf_amount": 146480, "gf_province": "เชียงราย", "bb_amount": null, "bb_province": "เชียงราย"}, {"gf_amount": 144600, "gf_province": "หนองบัวลำภู", "bb_amount": null, "bb_province": "หนองบัวลำภู"}, {"gf_amount": 137700, "gf_province": "อุตรดิตถ์", "bb_amount": null, "bb_province": "อุตรดิตถ์"}], "gf_amount_sum": 29355508.4}
{"bb_code": "1500853002500021", "bb_year": "2561", "amount": 28868800, "min_code": "15000", "agc_code": "15008", "name": "เงินอุดหนุนสำหรับสนับสนุนการจัดการศึกษาขององค์กรปกครองส่วนท้องถิ่นในพื้นที่จังหวัดชายแดนภาคใต้", "min": "กระทรวงมหาดไทย", "agc": "กรมส่งเสริมการปกครองท้องถิ่น", "plan_name": "แผนงานบูรณาการส่งเสริมการกระจายอำนาจให้แก่องค์กรปกครองส่วนท้องถิ่น", "stg_name": "ยุทธศาสตร์ด้านการปรับสมดุลและพัฒนาระบบบริหารจัดการภาครัฐ", "objc_level1_name": "งบอุดหนุน", "compare": [{"bb_amount": 28868800, "bb_province": "กรุงเทพมหานคร", "gf_amount": 28489200, "gf_province": "ส่วนกลาง"}], "gf_amount_sum": 28489200}
{"bb_code": "1500747026420133", "bb_year": "2561", "amount": 28000000, "min_code": "15000", "agc_code": "15007", "name": "ค่าจ้างที่ปรึกษาสำรวจออกแบบเขื่อนป้องกันตลิ่งริมแม่น้ำชายแดน ระยะที่ 5(สัญญา 2)", "min": "กระทรวงมหาดไทย", "agc": "กรมโยธาธิการและผังเมือง", "plan_name": "แผนงานยุทธศาสตร์จัดการผลกระทบจากการเปลี่ยนแปลงสภาวะภูมิอากาศ และภัยพิบัติ", "stg_name": "ยุทธศาสตร์ด้านการจัดการน้ำและสร้างการเติบโตบนคุณภาพชีวิตที่เป็นมิตรกับสิ่งแวดล้อมอย่างยั่งยืน", "objc_level1_name": "งบลงทุน", "compare": [{"bb_amount": 28000000, "bb_province": "กรุงเทพมหานคร", "gf_amount": 27960000, "gf_province": "ส่วนกลาง"}], "gf_amount_sum": 27960000}
{"bb_code": "1500747026420026", "bb_year": "2561", "amount": 28000000, "min_code": "15000", "agc_code": "15007", "name": "ค่าจ้างที่ปรึกษาสำรวจออกแบบเขื่อนป้องกันตลิ่งริมแม่น้ำชายแดน ระยะที่ 5(สัญญา 1)", "min": "กระทรวงมหาดไทย", "agc": "กรมโยธาธิการและผังเมือง", "plan_name": "แผนงานยุทธศาสตร์จัดการผลกระทบจากการเปลี่ยนแปลงสภาวะภูมิอากาศ และภัยพิบัติ", "stg_name": "ยุทธศาสตร์ด้านการจัดการน้ำและสร้างการเติบโตบนคุณภาพชีวิตที่เป็นมิตรกับสิ่งแวดล้อมอย่างยั่งยืน", "objc_level1_name": "งบลงทุน", "compare": [{"bb_amount": 28000000, "bb_province": "กรุงเทพมหานคร", "gf_amount": 27960000, "gf_province": "ส่วนกลาง"}], "gf_amount_sum": 27960000}
{"bb_code": "1500953047600013", "bb_year": "2561", "amount": 27650000, "min_code": "15000", "agc_code": "15009", "name": "โครงการก่อสร้างระบบระบายน้ำเพื่อแก้ไขปัญหาน้ำท่วมถนนนราธิวาสราชนครินทร์ 17และถนนสวนพลู", "min": "กระทรวงมหาดไทย", "agc": "กรุงเทพมหานคร", "plan_name": "แผนงานบูรณาการส่งเสริมการกระจายอำนาจให้แก่องค์กรปกครองส่วนท้องถิ่น", "stg_name": "ยุทธศาสตร์ด้านการปรับสมดุลและพัฒนาระบบบริหารจัดการภาครัฐ", "objc_level1_name": "งบอุดหนุน", "compare": [{"bb_amount": 27650000, "bb_province": "กรุงเทพมหานคร", "gf_amount": 0, "gf_province": "ส่วนกลาง"}], "gf_amount_sum": 0}
{"bb_code": "1500256039120004", "bb_year": "2561", "amount": 27300000, "min_code": "15000", "agc_code": "15002", "name": "ค่าระบบรักษาความปลอดภัยของอุปกรณ์สารสนเทศและการสื่อสาร (ดับเพลิง) แขวงบางขุนพรหม เขตพระนครกรุงเทพมหานคร", "min": "กระทรวงมหาดไทย", "agc": "สำนักงานปลัดกระทรวงมหาดไทย", "plan_name": "แผนงานยุทธศาสตร์พัฒนาประสิทธิภาพการบริหารราชการแผ่นดิน", "stg_name": "ยุทธศาสตร์ด้านการปรับสมดุลและพัฒนาระบบบริหารจัดการภาครัฐ", "objc_level1_name": "งบลงทุน", "compare": [{"bb_amount": 27300000, "bb_province": "กรุงเทพมหานคร", "gf_amount": 0, "gf_province": "ส่วนกลาง"}], "gf_amount_sum": 0}
{"bb_code": "1500542035000000", "bb_year": "2561", "amount": 26762000, "min_code": "15000", "agc_code": "15005", "name": "รายการงบประจำ", "min": "กระทรวงมหาดไทย", "agc": "กรมที่ดิน", "plan_name": "แผนงานบูรณาการจัดการปัญหาที่ดินทำกิน ", "stg_name": "ยุทธศาสตร์ด้านการจัดการน้ำและสร้างการเติบโตบนคุณภาพชีวิตที่เป็นมิตรกับสิ่งแวดล้อมอย่างยั่งยืน", "objc_level1_name": "งบดำเนินงาน", "compare": [{"bb_amount": 26762000, "bb_province": "กรุงเทพมหานคร", "gf_amount": 1704303.43, "gf_province": "ส่วนกลาง"}, {"gf_amount": 682677.5, "gf_province": "แม่ฮ่องสอน", "bb_amount": null, "bb_province": "แม่ฮ่องสอน"}, {"gf_amount": 599320, "gf_province": "น่าน", "bb_amount": null, "bb_province": "น่าน"}, {"gf_amount": 559199.07, "gf_province": "ชุมพร", "bb_amount": null, "bb_province": "ชุมพร"}, {"gf_amount": 543899.5, "gf_province": "เชียงใหม่", "bb_amount": null, "bb_province": "เชียงใหม่"}, {"gf_amount": 498800, "gf_province": "หนองคาย", "bb_amount": null, "bb_province": "หนองคาย"}, {"gf_amount": 494450, "gf_province": "เพชรบูรณ์", "bb_amount": null, "bb_province": "เพชรบูรณ์"}, {"gf_amount": 463754, "gf_province": "จันทบุรี", "bb_amount": null, "bb_province": "จันทบุรี"}, {"gf_amount": 436600, "gf_province": "พิษณุโลก", "bb_amount": null, "bb_province": "พิษณุโลก"}, {"gf_amount": 416597.1, "gf_province": "ระนอง", "bb_amount": null, "bb_province": "ระนอง"}, {"gf_amount": 413399.69, "gf_province": "อุดรธานี", "bb_amount": null, "bb_province": "อุดรธานี"}, {"gf_amount": 412944, "gf_province": "ตาก", "bb_amount": null, "bb_province": "ตาก"}, {"gf_amount": 396199, "gf_province": "สระบุรี", "bb_amount": null, "bb_province": "สระบุรี"}, {"gf_amount": 382295, "gf_province": "ลำพูน", "bb_amount": null, "bb_province": "ลำพูน"}, {"gf_amount": 379814, "gf_province": "มหาสารคาม", "bb_amount": null, "bb_province": "มหาสารคาม"}, {"gf_amount": 364790, "gf_province": "ลำปาง", "bb_amount": null, "bb_province": "ลำปาง"}, {"gf_amount": 358200, "gf_province": "อำนาจเจริญ", "bb_amount": null, "bb_province": "อำนาจเจริญ"}, {"gf_amount": 351700, "gf_province": "สตูล", "bb_amount": null, "bb_province": "สตูล"}, {"gf_amount": 341400, "gf_province": "พะเยา", "bb_amount": null, "bb_province": "พะเยา"}, {"gf_amount": 332460, "gf_province": "สงขลา", "bb_amount": null, "bb_province": "สงขลา"}, {"gf_amount": 324600, "gf_province": "แพร่", "bb_amount": null, "bb_province": "แพร่"}, {"gf_amount": 324546.02, "gf_province": "สระแก้ว", "bb_amount": null, "bb_province": "สระแก้ว"}, {"gf_amount": 312682.2, "gf_province": "ประจวบคีรีขันธ์", "bb_amount": null, "bb_province": "ประจวบคีรีขันธ์"}, {"gf_amount": 302125.5, "gf_province": "สกลนคร", "bb_amount": null, "bb_province": "สกลนคร"}, {"gf_amount": 293095, "gf_province": "มุกดาหาร", "bb_amount": null, "bb_province": "มุกดาหาร"}, {"gf_amount": 290100, "gf_province": "หนองบัวลำภู", "bb_amount": null, "bb_province": "หนองบัวลำภู"}, {"gf_amount": 290100, "gf_province": "อุบลราชธานี", "bb_amount": null, "bb_province": "อุบลราชธานี"}, {"gf_amount": 289100, "gf_province": "ร้อยเอ็ด", "bb_amount": null, "bb_province": "ร้อยเอ็ด"}, {"gf_amount": 289000, "gf_province": "ลพบุรี", "bb_amount": null, "bb_province": "ลพบุรี"}, {"gf_amount": 288960, "gf_province": "นครศรีธรรมราช", "bb_amount": null, "bb_province": "นครศรีธรรมราช"}, {"gf_amount": 281260, "gf_province": "ขอนแก่น", "bb_amount": null, "bb_province": "ขอนแก่น"}, {"gf_amount": 275439.4, "gf_province": "นนทบุรี", "bb_amount": null, "bb_province": "นนทบุรี"}, {"gf_amount": 267266, "gf_province": "ยโสธร", "bb_amount": null, "bb_province": "ยโสธร"}, {"gf_amount": 267090, "gf_province": "เพชรบุรี", "bb_amount": null, "bb_province": "เพชรบุรี"}, {"gf_amount": 251210, "gf_province": "นครราชสีมา", "bb_amount": null, "bb_province": "นครราชสีมา"}, {"gf_amount": 245134, "gf_province": "ศรีสะเกษ", "bb_amount": null, "bb_province": "ศรีสะเกษ"}, {"gf_amount": 235220, "gf_province": "สุรินทร์", "bb_amount": null, "bb_province": "สุรินทร์"}, {"gf_amount": 223094, "gf_province": "บุรีรัมย์", "bb_amount": null, "bb_province": "บุรีรัมย์"}, {"gf_amount": 221695, "gf_province": "สุพรรณบุรี", "bb_amount": null, "bb_province": "สุพรรณบุรี"}, {"gf_amount": 220000, "gf_province": "ตรัง", "bb_amount": null, "bb_province": "ตรัง"}, {"gf_amount": 200000, "gf_province": "กระบี่", "bb_amount": null, "bb_province": "กระบี่"}, {"gf_amount": 161696, "gf_province": "พัทลุง", "bb_amount": null, "bb_province": "พัทลุง"}, {"gf_amount": 160922, "gf_province": "ปัตตานี", "bb_amount": null, "bb_province": "ปัตตานี"}, {"gf_amount": 155878, "gf_province": "นราธิวาส", "bb_amount": null, "bb_province": "นราธิวาส"}, {"gf_amount": 56900, "gf_province": "เชียงราย", "bb_amount": null, "bb_province": "เชียงราย"}, {"gf_amount": 16840, "gf_province": "กาญจนบุรี", "bb_amount": null, "bb_province": "กาญจนบุรี"}], "gf_amount_sum": 16376755.41}
{"bb_code": "1500746037700065", "bb_year": "2561", "amount": 26000000, "min_code": "15000", "agc_code": "15007", "name": "โครงการจัดทำผังรายละเอียดโครงการคมนาคมและขนส่งตามผังเมืองรวม", "min": "กระทรวงมหาดไทย", "agc": "กรมโยธาธิการและผังเมือง", "plan_name": "แผนงานยุทธศาสตร์อนุรักษ์ ฟื้นฟู และป้องกันทรัพยากรธรรมชาติ", "stg_name": "ยุทธศาสตร์ด้านการจัดการน้ำและสร้างการเติบโตบนคุณภาพชีวิตที่เป็นมิตรกับสิ่งแวดล้อมอย่างยั่งยืน", "objc_level1_name": "รายจ่ายอื่น", "compare": [{"bb_amount": 26000000, "bb_province": "กรุงเทพมหานคร", "gf_amount": 0, "gf_province": "ส่วนกลาง"}], "gf_amount_sum": 0}
{"bb_code": "1500716033700001", "bb_year": "2561", "amount": 25910900, "min_code": "15000", "agc_code": "15007", "name": "ค่าใช้จ่ายในการจัดทำฐานข้อมูลดิจิทัลด้านการผังเมือง", "min": "กระทรวงมหาดไทย", "agc": "กรมโยธาธิการและผังเมือง", "plan_name": "แผนงานบูรณาการพัฒนาเศรษฐกิจดิจิทัล ", "stg_name": "ยุทธศาสตร์ด้านการสร้างความสามารถในการแข่งขันของประเทศ", "objc_level1_name": "รายจ่ายอื่น", "compare": [{"bb_amount": 25910900, "bb_province": "กรุงเทพมหานคร", "gf_amount": 11000000, "gf_province": "ส่วนกลาง"}], "gf_amount_sum": 11000000}
{"bb_code": "1500647020120006", "bb_year": "2561", "amount": 24850000, "min_code": "15000", "agc_code": "15006", "name": "สะพานถอดประกอบได้พร้อมชุดทอดสะพาน (Baileybridge) ขนาดผิวจราจรไม่น้อยกว่า 3 เมตร ความยาว 48 เมตร1 ชุด กรมป้องกันและบรรเทาสาธารณภัย แขวงดุสิตเขตดุสิต กรุงเทพมหานคร", "min": "กระทรวงมหาดไทย", "agc": "กรมป้องกันและบรรเทาสาธารณภัย", "plan_name": "แผนงานยุทธศาสตร์จัดการผลกระทบจากการเปลี่ยนแปลงสภาวะภูมิอากาศ และภัยพิบัติ", "stg_name": "ยุทธศาสตร์ด้านการจัดการน้ำและสร้างการเติบโตบนคุณภาพชีวิตที่เป็นมิตรกับสิ่งแวดล้อมอย่างยั่งยืน", "objc_level1_name": "งบลงทุน", "compare": [{"bb_amount": 24850000, "bb_province": "กรุงเทพมหานคร", "gf_amount": 24830000, "gf_province": "ส่วนกลาง"}], "gf_amount_sum": 24830000}
{"bb_code": "1500853002500034", "bb_year": "2561", "amount": 24570000, "min_code": "15000", "agc_code": "15008", "name": "เงินอุดหนุนสำหรับสนับสนุนการจัดการศึกษาแก่เด็กด้อยโอกาส (ค่าจ้างครู)", "min": "กระทรวงมหาดไทย", "agc": "กรมส่งเสริมการปกครองท้องถิ่น", "plan_name": "แผนงานบูรณาการส่งเสริมการกระจายอำนาจให้แก่องค์กรปกครองส่วนท้องถิ่น", "stg_name": "ยุทธศาสตร์ด้านการปรับสมดุลและพัฒนาระบบบริหารจัดการภาครัฐ", "objc_level1_name": "งบอุดหนุน", "compare": [{"bb_amount": 24570000, "bb_province": "กรุงเทพมหานคร", "gf_amount": 24570000, "gf_province": "ส่วนกลาง"}], "gf_amount_sum": 24570000}
{"bb_code": "1500746030420087", "bb_year": "2561", "amount": 24489200, "min_code": "15000", "agc_code": "15007", "name": "ค่ากำจัดสิ่งกีดขวางการจราจรทางน้ำ", "min": "กระทรวงมหาดไทย", "agc": "กรมโยธาธิการและผังเมือง", "plan_name": "แผนงานยุทธศาสตร์อนุรักษ์ ฟื้นฟู และป้องกันทรัพยากรธรรมชาติ", "stg_name": "ยุทธศาสตร์ด้านการจัดการน้ำและสร้างการเติบโตบนคุณภาพชีวิตที่เป็นมิตรกับสิ่งแวดล้อมอย่างยั่งยืน", "objc_level1_name": "งบลงทุน", "compare": [{"bb_amount": 24489200, "bb_province": "กรุงเทพมหานคร", "gf_amount": 24452398.71, "gf_province": "ส่วนกลาง"}], "gf_amount_sum": 24452398.71}
{"bb_code": "1500746037700082", "bb_year": "2561", "amount": 24000000, "min_code": "15000", "agc_code": "15007", "name": "โครงการจัดทำผังรายละเอียดโครงการกิจการสาธารณูปโภคตามผังเมืองรวม", "min": "กระทรวงมหาดไทย", "agc": "กรมโยธาธิการและผังเมือง", "plan_name": "แผนงานยุทธศาสตร์อนุรักษ์ ฟื้นฟู และป้องกันทรัพยากรธรรมชาติ", "stg_name": "ยุทธศาสตร์ด้านการจัดการน้ำและสร้างการเติบโตบนคุณภาพชีวิตที่เป็นมิตรกับสิ่งแวดล้อมอย่างยั่งยืน", "objc_level1_name": "รายจ่ายอื่น", "compare": [{"bb_amount": 24000000, "bb_province": "กรุงเทพมหานคร", "gf_amount": 0, "gf_province": "ส่วนกลาง"}], "gf_amount_sum": 0}
