{"bb_code": "1500883002600FF2", "bb_year": "2559", "amount": 3450600, "min_code": "15000", "agc_code": "15008", "name": "เสริมผิวลาดยางแอสฟัลท์ติกคอนกรีต แยก ทช.นค.๓๐๐๕ (หมู่บ้านที่ ๗+๘๐๐) - น้ำตกห้วยหินขาว กว้าง ๖ เมตร ยาว ๑,๕๖๐ เมตร อบต.ด่านศรีสุข อ.โพธิ์ตาก จ.หนองคาย", "min": "กระทรวงมหาดไทย", "agc": "กรมส่งเสริมการปกครองท้องถิ่น", "plan_name": "ส่งเสริมการกระจายอำนาจให้แก่องค์กรปกครองส่วนท้องถิ่น", "stg_name": "ยุทธศาสตร์การบริหารกิจการบ้านเมืองที่ดี", "objc_level1_name": "งบลงทุน", "compare": [{"bb_amount": 3450600, "bb_province": "หนองคาย"}], "gf_amount_sum": 0}
{"bb_code": "1500883002600AJ0", "bb_year": "2559", "amount": 3449200, "min_code": "15000", "agc_code": "15008", "name": "ซ่อมสร้างถนนคอนกรีตเสริมเหล็กบ้านคลองโต๊ะนุ้ย หมู่ที่ ๒ เชื่อม หมู่ที่ ๓ ตำบลขุนศรี พื้นที่ไม่น้อยกว่า ๓,๖๔๘ ตารางเมตร  อบต.ขุนศรี อ.ไทรน้อย จ.นนทบุรี", "min": "กระทรวงมหาดไทย", "agc": "กรมส่งเสริมการปกครองท้องถิ่น", "plan_name": "ส่งเสริมการกระจายอำนาจให้แก่องค์กรปกครองส่วนท้องถิ่น", "stg_name": "ยุทธศาสตร์การบริหารกิจการบ้านเมืองที่ดี", "objc_level1_name": "งบลงทุน", "compare": [{"bb_amount": 3449200, "bb_province": "นนทบุรี"}], "gf_amount_sum": 0}
{"bb_code": "1500883002600Y86", "bb_year": "2559", "amount": 3448600, "min_code": "15000", "agc_code": "15008", "name": "ซ่อมสร้างถนนลาดยางแอสฟัลท์ติกคอนกรีตสายบ้านบาโงตือบู หมู่ที่ ๒ บ้านบาโงตือบู ตำบลกายูคละ กว้าง ๔ เมตร ยาว ๒,๐๕๐ เมตร หนา ๐.๐๕ เมตร หรือมีพื้นที่ไม่น้อยกว่า ๘,๒๐๐ ตารางเมตร อบต.กายูคละ อ.แว้ง จ.นราธิวา", "min": "กระทรวงมหาดไทย", "agc": "กรมส่งเสริมการปกครองท้องถิ่น", "plan_name": "ส่งเสริมการกระจายอำนาจให้แก่องค์กรปกครองส่วนท้องถิ่น", "stg_name": "ยุทธศาสตร์การบริหารกิจการบ้านเมืองที่ดี", "objc_level1_name": "งบลงทุน", "compare": [{"bb_amount": 3448600, "bb_province": "นราธิวาส"}], "gf_amount_sum": 0}
{"bb_code": "1500883002600BU6", "bb_year": "2559", "amount": 3448600, "min_code": "15000", "agc_code": "15008", "name": "ซ่อมสร้างผิวทางจราจรแอสฟัลท์ติกคอนกรีต สายบ้านใหม่สี่หมื่น - วัดคูหาสวรรค์ กว้าง ๖ เมตร ยาว ๑,๑๙๒ เมตร หนา ๐.๐๕ เมตร  อบต.สี่หมื่น อ.ดำเนินสะดวก จ.ราชบุรี", "min": "กระทรวงมหาดไทย", "agc": "กรมส่งเสริมการปกครองท้องถิ่น", "plan_name": "ส่งเสริมการกระจายอำนาจให้แก่องค์กรปกครองส่วนท้องถิ่น", "stg_name": "ยุทธศาสตร์การบริหารกิจการบ้านเมืองที่ดี", "objc_level1_name": "งบลงทุน", "compare": [{"bb_amount": 3448600, "bb_province": "ราชบุรี"}], "gf_amount_sum": 0}
{"bb_code": "1500883002600DI5", "bb_year": "2559", "amount": 3442800, "min_code": "15000", "agc_code": "15008", "name": "ปรับปรุงถนนลาดยางแอสฟัลท์ติกคอนกรีต ( สาย อบจ.นม.๐๒๑๐๒ ) บ้านเทพนิมิต - บ้านประดู่งาม ขนาดกว้าง ๘ เมตร ยาว ๑,๒๒๙ เมตร หนา ๐.๐๔ เมตร  อบจ.นครราชสีมา อ.ครบุรี จ.นครราชสีมา", "min": "กระทรวงมหาดไทย", "agc": "กรมส่งเสริมการปกครองท้องถิ่น", "plan_name": "ส่งเสริมการกระจายอำนาจให้แก่องค์กรปกครองส่วนท้องถิ่น", "stg_name": "ยุทธศาสตร์การบริหารกิจการบ้านเมืองที่ดี", "objc_level1_name": "งบลงทุน", "compare": [{"bb_amount": 3442800, "bb_province": "นครราชสีมา"}], "gf_amount_sum": 0}
{"bb_code": "1500822040600D46", "bb_year": "2559", "amount": 3442500, "min_code": "15000", "agc_code": "15008", "name": "ก่อสร้างระบบประปาหมู่บ้าน แบบผิวดินขนาดใหญ่ บ้านโนนเจดีย์พัฒนา หมู่ที่ ๑๙ ตำบลบัลลังก์ ตามแบบมาตรฐานกรมทรัพยากรน้ำ ทต.บัลลังก์ อ.โนนไทย จ.นครราชสีมา", "min": "กระทรวงมหาดไทย", "agc": "กรมส่งเสริมการปกครองท้องถิ่น", "plan_name": "บริหารจัดการทรัพยากรน้ำ", "stg_name": "ยุทธศาสตร์เร่งรัดวางรากฐานการพัฒนาที่ยั่งยืนของประเทศ", "objc_level1_name": "งบลงทุน", "compare": [{"bb_amount": 3442500, "bb_province": "นครราชสีมา"}], "gf_amount_sum": 0}
{"bb_code": "1500822040600750", "bb_year": "2559", "amount": 3441500, "min_code": "15000", "agc_code": "15008", "name": "ก่อสร้างระบบประปาหมู่บ้านแบบบาดาลขนาดใหญ่มาก หมู่ที่ ๓ บ้านไร่ป่า ตำบลเนินทราย ตามแบบมาตรฐานกรมทรัพยากรน้ำ อบต.เนินทราย อ.เมืองตราด จ.ตราด", "min": "กระทรวงมหาดไทย", "agc": "กรมส่งเสริมการปกครองท้องถิ่น", "plan_name": "บริหารจัดการทรัพยากรน้ำ", "stg_name": "ยุทธศาสตร์เร่งรัดวางรากฐานการพัฒนาที่ยั่งยืนของประเทศ", "objc_level1_name": "งบลงทุน", "compare": [{"bb_amount": 3441500, "bb_province": "ตราด"}], "gf_amount_sum": 0}
{"bb_code": "1500822040600BC4", "bb_year": "2559", "amount": 3441500, "min_code": "15000", "agc_code": "15008", "name": "ก่อสร้างระบบประปาหมู่บ้าน แบบบาดาลขนาดใหญ่ หมู่ที่ ๖ บ้านตีนคลอง ตำบลอินคีรี รายละเอียดตามปริมาณงานและแบบแปลนที่องค์การบริหารส่วนตำบลอินคีรีกำหนด อบต.อินคีรี อ.พรหมคีรี จ.นครศรีธรรมราช", "min": "กระทรวงมหาดไทย", "agc": "กรมส่งเสริมการปกครองท้องถิ่น", "plan_name": "บริหารจัดการทรัพยากรน้ำ", "stg_name": "ยุทธศาสตร์เร่งรัดวางรากฐานการพัฒนาที่ยั่งยืนของประเทศ", "objc_level1_name": "งบลงทุน", "compare": [{"bb_amount": 3441500, "bb_province": "นครศรีธรรมราช"}], "gf_amount_sum": 0}
{"bb_code": "1500822040600Z32", "bb_year": "2559", "amount": 3440500, "min_code": "15000", "agc_code": "15008", "name": "ก่อสร้างระบบประปาหมู่บ้าน แบบผิวดินขนาดใหญ่ หมู่ที่ ๔ บ้านต้าย ตำบลนากั้ง ตามแบบมาตรฐานกรมทรัพยากรน้ำ อบต.นากั้ง อ.ปากคาด จ.บึงกาฬ", "min": "กระทรวงมหาดไทย", "agc": "กรมส่งเสริมการปกครองท้องถิ่น", "plan_name": "บริหารจัดการทรัพยากรน้ำ", "stg_name": "ยุทธศาสตร์เร่งรัดวางรากฐานการพัฒนาที่ยั่งยืนของประเทศ", "objc_level1_name": "งบลงทุน", "compare": [{"bb_amount": 3440500, "bb_province": "บึงกาฬ"}], "gf_amount_sum": 0}
{"bb_code": "1500822040600H83", "bb_year": "2559", "amount": 3440500, "min_code": "15000", "agc_code": "15008", "name": "ก่อสร้างระบบประปาหมู่บ้านแบบผิวดินขนาดใหญ่ หมู่ที่ ๙ บ้านโป่งตุ ตำบลเขากระปุก ตามแบบมาตรฐานกรมทรัพยากรน้ำ อบต.เขากระปุก อ.ท่ายาง จ.เพชรบุรี", "min": "กระทรวงมหาดไทย", "agc": "กรมส่งเสริมการปกครองท้องถิ่น", "plan_name": "บริหารจัดการทรัพยากรน้ำ", "stg_name": "ยุทธศาสตร์เร่งรัดวางรากฐานการพัฒนาที่ยั่งยืนของประเทศ", "objc_level1_name": "งบลงทุน", "compare": [{"bb_amount": 3440500, "bb_province": "เพชรบุรี"}], "gf_amount_sum": 0}
{"bb_code": "1500822040600W54", "bb_year": "2559", "amount": 3440500, "min_code": "15000", "agc_code": "15008", "name": "ก่อสร้างประปาหมู่บ้านแบบผิวดินขนาดใหญ่ บ้านยางบึงหมู่ที่ ๓ ตำบลกุดสระ ตามแบบมาตรฐานกรมทรัพยากรน้ำ อบต.กุดสระ อ.เมืองอุดรธานี จ.อุดรธานี", "min": "กระทรวงมหาดไทย", "agc": "กรมส่งเสริมการปกครองท้องถิ่น", "plan_name": "บริหารจัดการทรัพยากรน้ำ", "stg_name": "ยุทธศาสตร์เร่งรัดวางรากฐานการพัฒนาที่ยั่งยืนของประเทศ", "objc_level1_name": "งบลงทุน", "compare": [{"bb_amount": 3440500, "bb_province": "อุดรธานี"}], "gf_amount_sum": 0}
{"bb_code": "1500883002600M83", "bb_year": "2559", "amount": 3437000, "min_code": "15000", "agc_code": "15008", "name": "ซ่อมสร้างถนนลาดยาง Cape Seal สายบ้านหนองแก - วัดสังกัสรัตนคีรี ตำบลหนองแก มีพื้นที่ไม่น้อยกว่า ๑๔,๔๐๐ ตารางเมตร อบจ.อุทัยธานี อ.เมืองอุทัยธานี จ.อุทัยธานี", "min": "กระทรวงมหาดไทย", "agc": "กรมส่งเสริมการปกครองท้องถิ่น", "plan_name": "ส่งเสริมการกระจายอำนาจให้แก่องค์กรปกครองส่วนท้องถิ่น", "stg_name": "ยุทธศาสตร์การบริหารกิจการบ้านเมืองที่ดี", "objc_level1_name": "งบลงทุน", "compare": [{"bb_amount": 3437000, "bb_province": "อุทัยธานี"}], "gf_amount_sum": 0}
{"bb_code": "1500785013410002", "bb_year": "2559", "amount": 3435400, "min_code": "15000", "agc_code": "15007", "name": "โครงการปรับปรุงถนนในชุมชน สายภายในหมู่บ้านหัวควน หมู่ที่ 6 ตำบลนาเกตุ อำเภอโคกโพธิ์ จังหวัดปัตตานี กว้าง 5 ม. ระยะทาง 1.720 กม. หมู่บ้านพื้นที่ระดับ 3", "min": "กระทรวงมหาดไทย", "agc": "กรมโยธาธิการและผังเมือง", "plan_name": "แก้ไขปัญหาและพัฒนาจังหวัดชายแดนภาคใต้", "stg_name": "ยุทธศาสตร์เร่งรัดวางรากฐานการพัฒนาที่ยั่งยืนของประเทศ", "objc_level1_name": "งบลงทุน", "compare": [{"bb_amount": 3435400, "bb_province": "ปัตตานี", "gf_amount": 3435400, "gf_province": "ปัตตานี"}], "gf_amount_sum": 3435400}
{"bb_code": "1500822040600F23", "bb_year": "2559", "amount": 3433600, "min_code": "15000", "agc_code": "15008", "name": "ก่อสร้างระบบประปาหมู่บ้านแบบผิวดินขนาดใหญ่ หมู่ ๖ บ้านบัวตารุ้ง ตำบลนางรอง ตามแบบมาตรฐานกรมทรัพยากรน้ำ อบต.นางรอง อ.นางรอง จ.บุรีรัมย์", "min": "กระทรวงมหาดไทย", "agc": "กรมส่งเสริมการปกครองท้องถิ่น", "plan_name": "บริหารจัดการทรัพยากรน้ำ", "stg_name": "ยุทธศาสตร์เร่งรัดวางรากฐานการพัฒนาที่ยั่งยืนของประเทศ", "objc_level1_name": "งบลงทุน", "compare": [{"bb_amount": 3433600, "bb_province": "บุรีรัมย์"}], "gf_amount_sum": 0}
{"bb_code": "1500883002600X84", "bb_year": "2559", "amount": 3433500, "min_code": "15000", "agc_code": "15008", "name": "ซ่อมสร้างถนนคอนกรีตเสริมเหล็ก สายชัยรุ่งเรือง - ศรีสมบูรณ์ กว้าง ๗ เมตร  ยาว ๙๕๘ เมตร  หนาเฉลี่ย ๐.๑๕ เมตร  ไหล่ทางกว้างข้างละ ๐.๕๐ เมตร  อบต.หนองโก อ.กระนวน จ.ขอนแก่น", "min": "กระทรวงมหาดไทย", "agc": "กรมส่งเสริมการปกครองท้องถิ่น", "plan_name": "ส่งเสริมการกระจายอำนาจให้แก่องค์กรปกครองส่วนท้องถิ่น", "stg_name": "ยุทธศาสตร์การบริหารกิจการบ้านเมืองที่ดี", "objc_level1_name": "งบลงทุน", "compare": [{"bb_amount": 3433500, "bb_province": "ขอนแก่น"}], "gf_amount_sum": 0}
{"bb_code": "1500883002600O86", "bb_year": "2559", "amount": 3433500, "min_code": "15000", "agc_code": "15008", "name": "ซ่อมสร้างถนนคอนกรีตเสริมเหล็กบ้านหนองสนุน - บ้านเนินสะเดา (นว.ถ ๖๙ - ๐๐๑) หมู่ที่ ๘ บ้านหนองสนุ่น, หมู่ที่ ๑๒ บ้านเนินสะเดา ตำบลบางเคียน กว้าง ๖ เมตร หนา ๐.๑๕ เมตร ยาว ๑,๑๐๐ เมตร พื้นที่ไม่น้อยกว่า ๖,", "min": "กระทรวงมหาดไทย", "agc": "กรมส่งเสริมการปกครองท้องถิ่น", "plan_name": "ส่งเสริมการกระจายอำนาจให้แก่องค์กรปกครองส่วนท้องถิ่น", "stg_name": "ยุทธศาสตร์การบริหารกิจการบ้านเมืองที่ดี", "objc_level1_name": "งบลงทุน", "compare": [{"bb_amount": 3433500, "bb_province": "นครสวรรค์"}], "gf_amount_sum": 0}
{"bb_code": "1500883002600O87", "bb_year": "2559", "amount": 3433500, "min_code": "15000", "agc_code": "15008", "name": "ซ่อมสร้างถนนคอนกรีตเสริมเหล็กบ้านคลองยาง - บ้านคลองคล้า (นว.ถ ๖๙ - ๐๐๒) หมู่ที่ ๑๑ บ้านคลองยาง , หมู่ที่ ๑ บ้านคลองคล้า ตำบลบางเคียน กว้าง ๖ เมตร หนา ๐.๑๕ เมตร ยาว ๑,๑๐๐ เมตร พื้นที่ไม่น้อยกว่า ๖,๖๐๐", "min": "กระทรวงมหาดไทย", "agc": "กรมส่งเสริมการปกครองท้องถิ่น", "plan_name": "ส่งเสริมการกระจายอำนาจให้แก่องค์กรปกครองส่วนท้องถิ่น", "stg_name": "ยุทธศาสตร์การบริหารกิจการบ้านเมืองที่ดี", "objc_level1_name": "งบลงทุน", "compare": [{"bb_amount": 3433500, "bb_province": "นครสวรรค์"}], "gf_amount_sum": 0}
{"bb_code": "1500883002600GY9", "bb_year": "2559", "amount": 3431200, "min_code": "15000", "agc_code": "15008", "name": "ซ่อมสร้างถนนลาดยางผิวแอสฟัลท์ติกคอนกรีต โดยวิธี Pavement in - place Recycling สายรอบคำชะโนด บ้านโนนเมือง หมู่ที่ ๑๑  กว้าง ๖ เมตร  ยาว ๑,๑๑๐ เมตร  อบต.บ้านม่วง อ.บ้านดุง จ.อุดรธานี", "min": "กระทรวงมหาดไทย", "agc": "กรมส่งเสริมการปกครองท้องถิ่น", "plan_name": "ส่งเสริมการกระจายอำนาจให้แก่องค์กรปกครองส่วนท้องถิ่น", "stg_name": "ยุทธศาสตร์การบริหารกิจการบ้านเมืองที่ดี", "objc_level1_name": "งบลงทุน", "compare": [{"bb_amount": 3431200, "bb_province": "อุดรธานี"}], "gf_amount_sum": 0}
{"bb_code": "1500883002600W05", "bb_year": "2559", "amount": 3429300, "min_code": "15000", "agc_code": "15008", "name": "ซ่อมสร้างถนนลาดยางผิวทางพาราแอสฟัลท์ติกคอนกรีต (โดยวิธี Pavement In - Place Recycling) สายบ้านโนนภูทอง หมู่ที่ ๑๒ ตำบลหนองหิน - บ้านเหล่าใหญ่ หมู่ที่ ๒ ตำบล ปวนพุ อำเภอหนองหิน กว้าง ๖ เมตร ยาว ๗๗๕ เมต", "min": "กระทรวงมหาดไทย", "agc": "กรมส่งเสริมการปกครองท้องถิ่น", "plan_name": "ส่งเสริมการกระจายอำนาจให้แก่องค์กรปกครองส่วนท้องถิ่น", "stg_name": "ยุทธศาสตร์การบริหารกิจการบ้านเมืองที่ดี", "objc_level1_name": "งบลงทุน", "compare": [{"bb_amount": 3429300, "bb_province": "เลย"}], "gf_amount_sum": 0}
{"bb_code": "1500822040600D49", "bb_year": "2559", "amount": 3428700, "min_code": "15000", "agc_code": "15008", "name": "ก่อสร้างระบบประปาหมู่บ้าน แบบผิวดินขนาดใหญ่ บ้านค้างพลูใต้ หมู่ที่ ๓ ตำบลค้างพลู  ตามแบบมาตรฐานกรมทรัพยากรน้ำ อบต.ค้างพลู อ.โนนไทย จ.นครราชสีมา", "min": "กระทรวงมหาดไทย", "agc": "กรมส่งเสริมการปกครองท้องถิ่น", "plan_name": "บริหารจัดการทรัพยากรน้ำ", "stg_name": "ยุทธศาสตร์เร่งรัดวางรากฐานการพัฒนาที่ยั่งยืนของประเทศ", "objc_level1_name": "งบลงทุน", "compare": [{"bb_amount": 3428700, "bb_province": "นครราชสีมา"}], "gf_amount_sum": 0}
